<?xml version="1.0" encoding="UTF-8"?>
<ProgrammesList>
  <Programme programme_id="15" programme_code="RSD">
    <programme_name>Software System Development</programme_name>
    <programme_desc>Programmer</programme_desc>
    <fulltime_duration>2</fulltime_duration>
    <parttime_duration>2</parttime_duration>
    <profcer>Software Engineering</profcer>
    <MER_SPM>2</MER_SPM>
    <MER_STPM>2</MER_STPM>
    <MER_UEC>2</MER_UEC>
    <MER_desc>Pass in English</MER_desc>
    <faculty>Faculty Of Computer Science</faculty>
  </Programme>
  <Programme programme_id="16" programme_code="RAC">
    <programme_name>Accounting</programme_name>
    <programme_desc>Business</programme_desc>
    <fulltime_duration>2</fulltime_duration>
    <parttime_duration>2</parttime_duration>
    <profcer>Finance Accounting</profcer>
    <MER_SPM>2</MER_SPM>
    <MER_STPM>2</MER_STPM>
    <MER_UEC>2</MER_UEC>
    <MER_desc>Pass in English</MER_desc>
    <faculty>Faculty Of Computer Science</faculty>
  </Programme>
</ProgrammesList>
